{
  "types": {
    "aliases": "aliases",
    "cssclasses": "multitext",
    "tags": "tags",
    "woundLevel": "multitext",
    "health-status": "text",
    "ATT": "number",
    "DEF": "number",
    "MISSILE": "number",
    "ARMOR": "text",
    "name": "text",
    "rank": "multitext",
    "AIM": "number",
    "MOVE": "text",
    "LD": "number",
    "#ATT": "number",
    "COU": "number",
    "DIS": "number",
    "virtue-level": "number",
    "char-name": "text",
    "": "number",
    "abilities": "multitext",
    "Text1": "text",
    "image": "text",
    "stats": "multitext",
    "fief-power": "text",
    "fief-troops": "number",
    "fief-wealth": "number",
    "fief-dissent": "number",
    "b1_stats": "multitext",
    "skills": "multitext"
  }
}